ritest/__init__.py
ritest/config.py
ritest/results.py
ritest/run.py
ritest/validation.py
ritest/ci/__init__.py
ritest/ci/coef_ci.py
ritest/ci/pvalue_ci.py
ritest/engine/fast_ols.py
ritest/engine/shuffle.py
ritest_python-0.1.1.dist-info/licenses/LICENSE
ritest_python-0.1.1.dist-info/METADATA
ritest_python-0.1.1.dist-info/WHEEL
ritest_python-0.1.1.dist-info/top_level.txt
ritest_python-0.1.1.dist-info/RECORD
