Metadata-Version: 2.4
Name: ritest-python
Version: 0.1.1
Summary: Randomization inference in Python.
Author: Tabaré Capitán
License: MIT License
Project-URL: homepage, https://tabarecapitan.com/projects/ritest
Project-URL: repository, https://github.com/tabarecapitan/ritest
Project-URL: issues, https://github.com/tabareCapitan/ritest/issues
Classifier: Development Status :: 3 - Alpha
Classifier: Intended Audience :: Science/Research
Classifier: License :: OSI Approved :: MIT License
Classifier: Programming Language :: Python
Classifier: Programming Language :: Python :: 3
Classifier: Programming Language :: Python :: 3.10
Classifier: Programming Language :: Python :: 3.11
Classifier: Programming Language :: Python :: 3.12
Classifier: Topic :: Scientific/Engineering
Classifier: Topic :: Scientific/Engineering :: Mathematics
Requires-Python: >=3.10
License-File: LICENSE
Requires-Dist: numpy
Requires-Dist: pandas
Requires-Dist: patsy
Requires-Dist: scipy
Requires-Dist: packaging
Provides-Extra: plot
Requires-Dist: matplotlib; extra == "plot"
Provides-Extra: numba
Requires-Dist: numba; extra == "numba"
Provides-Extra: test
Requires-Dist: pytest; extra == "test"
Requires-Dist: statsmodels; extra == "test"
Dynamic: license-file
